physethta/__init__.py
physethta/assigner.py
physethta/config.py
physethta/external.py
physethta/loader.py
physethta/report.py
physethta/run_assignment.py
physethta/utils.py
physethta/assets/Logo.pdf
physethta-1.0.4.dist-info/METADATA
physethta-1.0.4.dist-info/WHEEL
physethta-1.0.4.dist-info/entry_points.txt
physethta-1.0.4.dist-info/top_level.txt
physethta-1.0.4.dist-info/RECORD
