Metadata-Version: 2.4
Name: physethta
Version: 1.0.4
Summary: Assignment tool for physics TAs
Home-page: https://gitlab.phys.ethz.ch/sebastian.huber/physethta
Author: Sebastian Huber
Author-email: huberse@phys.ethz.ch
Requires-Python: >=3.8
Requires-Dist: pandas
Requires-Dist: pyyaml
Requires-Dist: openpyxl
Dynamic: author
Dynamic: author-email
Dynamic: description
Dynamic: description-content-type
Dynamic: home-page
Dynamic: requires-dist
Dynamic: requires-python
Dynamic: summary
